homeworkone/__init__.py
homeworkone/currpy.py
homeworkone-0.2.0.dist-info/METADATA
homeworkone-0.2.0.dist-info/WHEEL
homeworkone-0.2.0.dist-info/top_level.txt
homeworkone-0.2.0.dist-info/RECORD
