Metadata-Version: 2.1
Name: homeworkone
Version: 0.2.0
Summary: homeworkone python library
Home-page: https://medium-multiply.readthedocs.io/
Author: Jonathan Maravilla
Author-email: jonmaravilla@gmail.com
License: MIT
Classifier: Intended Audience :: Developers
Classifier: License :: OSI Approved :: MIT License
Classifier: Programming Language :: Python
Classifier: Programming Language :: Python :: 3
Classifier: Programming Language :: Python :: 3.6
Classifier: Programming Language :: Python :: 3.7
Classifier: Programming Language :: Python :: 3.8
Classifier: Programming Language :: Python :: 3.9
Classifier: Operating System :: OS Independent
Requires-Dist: datetime
Requires-Dist: time
Requires-Dist: polygon
Requires-Dist: sqlalchemy
Requires-Dist: pandas
Requires-Dist: math
Requires-Dist: matplotlib.pyplot
Requires-Dist: numpy
